{
  "connect": {
    "token": "E6AA8B3D48117DD302181DE627AD1FA1AE6C34AD",
    "username": "test",
    "email": "raphael.sebaon@epitech.eu",
    "firstName": "raphaelll",
    "lastName": "sebaon",
    "birthDay": "05/05/2020",
    "mail": "ebaon@epitech.eu"
  },
  "disconnect": {
    "email": "raphael.sebaon@epitech.eu"
  },
  "register": {
    "firstName": "François",
    "lastName": "MILHET",
    "birthDay": "2020-09-08",
    "username": "test",
    "email": "francois97180@hotmail.fr",
    "password": "test12345",
    "confirmPassword": "test12345",
    "recaptcha": ""
  },
  "resetPassword": {
    "email": "francois.milhet@gmail.om"
  },
  "contact": {
    "object": "Support",
    "content": "fsdsd",
    "name": "dd",
    "email": "francois.milhet@gmail.om"
  },
  "updateInfoUser": {
    "password": "dddddddd",
    "firstName": "François",
    "lastName": "MILHET",
    "userName": "SkuSku971",
    "email": "francois97180@hotmail.fr"
  },
  "listParts": {
    "keyWord": "pneus"
  },
  "item": {
    "name": "Pneu continental GT",
    "chartData": [
      {
        "month": "Janv",
        "price": "180"
      },
      {
        "month": "Fev",
        "price": "200"
      },
      {
        "month": "Mars",
        "price": "210"
      },
      {
        "month": "Avril",
        "price": "190"
      },
      {
        "month": "Mai",
        "price": "240"
      },
      {
        "month": "Juin",
        "price": "230"
      },
      {
        "month": "Juil",
        "price": "260"
      },
      {
        "month": "Aôut",
        "price": "210"
      },
      {
        "month": "Sept",
        "price": "300"
      },
      {
        "month": "Oct",
        "price": "210"
      },
      {
        "month": "Nov",
        "price": "210"
      },
      {
        "month": "Déc",
        "price": "210"
      }
    ],
    "details": {
      "brand": "Continental",
      "ref": "54031708",
      "year": "1997"
    },
    "description": "Le pneu continental GT pour voiture de collection est un pneu radial conventionnel qui apporte plus de sécurité. Ce profil continental apporte également une économie à l'usage et un plus grand confort grâce à la souplesse de ses flancs. Le continental GT équipe différentes catégories de voitures, des originales et populaires 2CV ou Coccinelleaux fascinantes Mercedes 190SL ou encore Facel Vega."
  }
}